
{
  "Compounds" : {
    "sodiumChloride" : {
      "anion" : "Cl",
      "cation" : "Na",
      "formula" : "NaCl",
      "anionCoefficient": 1,
      "cationCoefficient": 1,
      "solidInWater" : false
    },
    "litiumBromide" : {
      "anion" : "Br",
      "cation" : "Li",
      "formula" : "LiBr",
      "anionCoefficient": 1,
      "cationCoefficient": 1,
      "solidInWater" : false
    },
    "magnisiumChloride" : {
      "anion" : "Cl",
      "cation" : "Mg",
      "formula" : "MgCl2",
      "anionCoefficient": 2,
      "cationCoefficient": 1,
      "solidInWater" : false
    },
    "magnisiumBromide" : {
      "anion" : "Br",
      "cation" : "Mg",
      "formula" : "MgBr2",
      "anionCoefficient": 2,
      "cationCoefficient": 1,
      "solidInWater" : false
    },
    "sodiumBromide" : {
      "anion" : "Br",
      "cation" : "Na",
      "formula" : "NaBr",
      "anionCoefficient": 1,
      "cationCoefficient": 1,
      "solidInWater" : false
    },
    "litiumChloride" : {
      "anion" : "Cl",
      "cation" : "Li",
      "formula" : "LiCl",
      "anionCoefficient": 1,
      "cationCoefficient": 1,
      "solidInWater" : false
    },
    "magnisiumSulfate" : {
      "anion" : "SO4",
      "cation" : "Mg",
      "formula" : "MgSO4",
      "anionCoefficient": 1,
      "cationCoefficient": 1,
      "solidInWater" : false
    },
    "potassiumPermanganate" : {
      "anion" : "MnO4",
      "cation" : "K",
      "formula" : "KMnO4",
      "anionCoefficient": 1,
      "cationCoefficient": 1,
      "solidInWater" : false
    },
    "potassiumManganate" : {
      "anion" : "MnO4",
      "cation" : "K",
      "formula" : "KMnO4",
      "anionCoefficient": 1,
      "cationCoefficient": 2,
      "solidInWater" : false
    },

    "sodiumSulfate" : {
      "anion" : "SO4",
      "cation" : "Na",
      "formula" : "Na2SO4",
      "anionCoefficient": 1,
      "cationCoefficient": 2,
      "solidInWater" : false
    },
    "potassiumIodide" : {
      "anion" : "I",
      "cation" : "K",
      "formula" : "KI",
      "anionCoefficient": 1,
      "cationCoefficient": 1,
      "solidInWater" : false
    },
    "calciumChloride" : {
      "anion" : "Cl",
      "cation" : "Ca",
      "formula" : "CaCl2",
      "anionCoefficient": 2,
      "cationCoefficient": 1,
      "solidInWater" : false
    },
    "calciumBromide" : {
      "anion" : "Br",
      "cation" : "Ca",
      "formula" : "CaBr2",
      "anionCoefficient": 2,
      "cationCoefficient": 1,
      "solidInWater" : false
    },
    "calciumFluoride" : {
      "anion" : "Fl",
      "cation" : "Ca",
      "formula" : "CaFl2",
      "anionCoefficient": 2,
      "cationCoefficient": 1,
      "solidInWater" : false
    },
    "cupricChloride" : {
      "anion" : "Cl",
      "cation" : "Cu",
      "formula" : "CuCl2",
      "anionCoefficient": 2,
      "cationCoefficient": 1,
      "solidInWater" : false
    },
    "copperChloride" : {
      "anion" : "Cl",
      "cation" : "Cu",
      "formula" : "CuCl",
      "anionCoefficient": 1,
      "cationCoefficient": 1,
      "solidInWater" : false
    },
    "copperBromide" : {
      "anion" : "Br",
      "cation" : "Cu",
      "formula" : "CuBr",
      "anionCoefficient": 1,
      "cationCoefficient": 1,
      "solidInWater" : false
    },
    "cupricBromide" : {
      "anion" : "Br",
      "cation" : "Cu",
      "formula" : "CuBr2",
      "anionCoefficient": 2,
      "cationCoefficient": 1,
      "solidInWater" : false
    }
  },
  "Ions" : {
    "sodium" : {
      "charge" : 1,
      "formula" : "Na"
    },
    "litium" : {
      "charge" : 1,
      "formula" : "Li"
    },
    "magnisium" : {
      "charge" : 1,
      "formula" : "Mg"
    },
    "chloride" : {
      "charge" : -1,
      "formula" : "Cl"
    },
    "bromide" : {
      "charge" : -1,
      "formula" : "Br"
    },
    "sulfate" : {
      "charge" : -2,
      "formula" : "SO4"
    }
  }
}